{
  "resourceType": "StructureDefinition",
  "id": "au-primarycaremedication",
  "url": "https://aehrc.com/fhir/StructureDefinition/AUPrimaryCareMedication",
  "version": "0.0.1",
  "name": "AUPrimaryCareMedication",
  "title": "AU Primary Care Medication",
  "status": "draft",
  "experimental": false,
  "description": "This profile defines a medication structure that includes core localisation concepts for use in an Australian primary care practice-to-practice record transfer context.",
  "purpose": "This profile defines a medication structure that includes core localisation concepts for use in an Australian primary care practice-to-practice record transfer context.",
  "fhirVersion": "3.0.1",
  "kind": "resource",
  "abstract": false,
  "type": "Medication",
  "baseDefinition": "http://hl7.org.au/fhir/StructureDefinition/au-medication",
  "derivation": "constraint",
  "differential": {
    "element": [
      {
        "id": "Medication.extension:pbsSponsor",
        "path": "Medication.extension",
        "sliceName": "pbsSponsor",
        "max": "0"
      },
      {
        "id": "Medication.extension:strengthText",
        "path": "Medication.extension",
        "sliceName": "strengthText"
      },
      {
        "id": "Medication.extension:strengthText.value[x]:valueQuantity",
        "path": "Medication.extension.valueQuantity",
        "sliceName": "valueQuantity",
        "min": 1,
        "type": [
          {
            "code": "Quantity"
          }
        ]
      },
      {
        "id": "Medication.status",
        "path": "Medication.status",
        "max": "0"
      },
      {
        "id": "Medication.isBrand",
        "path": "Medication.isBrand",
        "max": "0"
      },
      {
        "id": "Medication.isOverTheCounter",
        "path": "Medication.isOverTheCounter",
        "max": "0"
      },
      {
        "id": "Medication.manufacturer",
        "path": "Medication.manufacturer",
        "max": "0"
      },
      {
        "id": "Medication.ingredient",
        "path": "Medication.ingredient",
        "max": "0"
      },
      {
        "id": "Medication.package",
        "path": "Medication.package",
        "max": "0"
      },
      {
        "id": "Medication.image",
        "path": "Medication.image",
        "max": "0"
      }
    ]
  }
}